{
    "config": {
        "view": {
            "continuousWidth": 300,
            "continuousHeight": 300
        }
    },
    "data": {
        "url": "https://cdn.jsdelivr.net/npm/vega-datasets@v1.29.0/data/world-110m.json",
        "format": {
            "feature": "countries",
            "type": "topojson"
        }
    },
    "mark": {
        "type": "geoshape",
        "stroke": "white",
        "strokeWidth": 0.5
    },
    "encoding": {
        "color": {
            "condition": {
                "test": "datum.download_mbps !== null",
                "field": "download_mbps",
                "scale": {
                    "scheme": "tealblues"
                },
                "title": "Avg. Download (Mbps)",
                "type": "quantitative"
            },
            "value": "#e0e0e0"
        },
        "tooltip": [{
            "field": "country_name",
            "title": "Country",
            "type": "nominal"
        }, {
            "field": "download_mbps",
            "format": ".2f",
            "title": "Avg. Download",
            "type": "quantitative"
        }]
    },
    "height": 500,
    "projection": {
        "type": "mercator"
    },
    "title": "Download Speeds",
    "transform": [{
        "lookup": "id",
        "from": {
            "data": {
                "name": "data-0d79c13841d81524131ceca720ecd61d"
            },
            "key": "id",
            "fields": ["country_name", "download_mbps"]
        }
    }],
    "width": 900,
    "$schema": "https://vega.github.io/schema/vega-lite/v5.20.1.json",
    "datasets": {
        "data-0d79c13841d81524131ceca720ecd61d": [{
            "id": 4,
            "country_name": "Afghanistan",
            "download_mbps": 3.564,
            "upload_mbps": 3.984
        }, {
            "id": 248,
            "country_name": "\u00c5land Islands",
            "download_mbps": 64.138,
            "upload_mbps": 52.179
        }, {
            "id": 8,
            "country_name": "Albania",
            "download_mbps": 13.911,
            "upload_mbps": 10.008
        }, {
            "id": 12,
            "country_name": "Algeria",
            "download_mbps": 3.492,
            "upload_mbps": 1.368
        }, {
            "id": 16,
            "country_name": "American Samoa",
            "download_mbps": 20.147,
            "upload_mbps": 6.948
        }, {
            "id": 20,
            "country_name": "Andorra",
            "download_mbps": 79.803,
            "upload_mbps": 77.195
        }, {
            "id": 24,
            "country_name": "Angola",
            "download_mbps": 10.083,
            "upload_mbps": 4.539
        }, {
            "id": 660,
            "country_name": "Anguilla",
            "download_mbps": 19.441,
            "upload_mbps": 8.736
        }, {
            "id": 10,
            "country_name": "Antarctica",
            "download_mbps": 41.993,
            "upload_mbps": 12.787
        }, {
            "id": 28,
            "country_name": "Antigua and Barbuda",
            "download_mbps": 11.191,
            "upload_mbps": 4.182
        }, {
            "id": 32,
            "country_name": "Argentina",
            "download_mbps": 17.892,
            "upload_mbps": 4.814
        }, {
            "id": 51,
            "country_name": "Armenia",
            "download_mbps": 15.51,
            "upload_mbps": 14.608
        }, {
            "id": 533,
            "country_name": "Aruba",
            "download_mbps": 66.163,
            "upload_mbps": 13.922
        }, {
            "id": 36,
            "country_name": "Australia",
            "download_mbps": 31.118,
            "upload_mbps": 11.839
        }, {
            "id": 40,
            "country_name": "Austria",
            "download_mbps": 32.509,
            "upload_mbps": 10.911
        }, {
            "id": 31,
            "country_name": "Azerbaijan",
            "download_mbps": 6.007,
            "upload_mbps": 5.045
        }, {
            "id": 44,
            "country_name": "Bahamas",
            "download_mbps": 26.186,
            "upload_mbps": 8.835
        }, {
            "id": 48,
            "country_name": "Bahrain",
            "download_mbps": 28.777,
            "upload_mbps": 7.725
        }, {
            "id": 50,
            "country_name": "Bangladesh",
            "download_mbps": 14.344,
            "upload_mbps": 18.422
        }, {
            "id": 52,
            "country_name": "Barbados",
            "download_mbps": 112.033,
            "upload_mbps": 53.734
        }, {
            "id": 112,
            "country_name": "Belarus",
            "download_mbps": 24.603,
            "upload_mbps": 20.106
        }, {
            "id": 56,
            "country_name": "Belgium",
            "download_mbps": 71.737,
            "upload_mbps": 14.574
        }, {
            "id": 84,
            "country_name": "Belize",
            "download_mbps": 27.001,
            "upload_mbps": 20.691
        }, {
            "id": 204,
            "country_name": "Benin",
            "download_mbps": 6.887,
            "upload_mbps": 4.683
        }, {
            "id": 60,
            "country_name": "Bermuda",
            "download_mbps": 50.851,
            "upload_mbps": 16.261
        }, {
            "id": 64,
            "country_name": "Bhutan",
            "download_mbps": 8.375,
            "upload_mbps": 10.725
        }, {
            "id": 70,
            "country_name": "Bosnia and Herzegovina",
            "download_mbps": 15.661,
            "upload_mbps": 3.483
        }, {
            "id": 72,
            "country_name": "Botswana",
            "download_mbps": 5.04,
            "upload_mbps": 3.719
        }, {
            "id": 76,
            "country_name": "Brazil",
            "download_mbps": 25.143,
            "upload_mbps": 15.73
        }, {
            "id": 96,
            "country_name": "Brunei Darussalam",
            "download_mbps": 18.966,
            "upload_mbps": 11.404
        }, {
            "id": 100,
            "country_name": "Bulgaria",
            "download_mbps": 32.883,
            "upload_mbps": 27.992
        }, {
            "id": 854,
            "country_name": "Burkina Faso",
            "download_mbps": 5.988,
            "upload_mbps": 5.784
        }, {
            "id": 104,
            "country_name": "Myanmar",
            "download_mbps": 12.29,
            "upload_mbps": 11.843
        }, {
            "id": 108,
            "country_name": "Burundi",
            "download_mbps": 7.944,
            "upload_mbps": 8.223
        }, {
            "id": 116,
            "country_name": "Cambodia",
            "download_mbps": 13.833,
            "upload_mbps": 15.006
        }, {
            "id": 120,
            "country_name": "Cameroon",
            "download_mbps": 10.757,
            "upload_mbps": 7.452
        }, {
            "id": 124,
            "country_name": "Canada",
            "download_mbps": 71.954,
            "upload_mbps": 26.56
        }, {
            "id": 136,
            "country_name": "Cayman Islands",
            "download_mbps": 26.39,
            "upload_mbps": 8.94
        }, {
            "id": 140,
            "country_name": "Central African Republic",
            "download_mbps": 2.652,
            "upload_mbps": 1.849
        }, {
            "id": 148,
            "country_name": "Chad",
            "download_mbps": 8.137,
            "upload_mbps": 4.872
        }, {
            "id": 152,
            "country_name": "Chile",
            "download_mbps": 49.394,
            "upload_mbps": 24.708
        }, {
            "id": 156,
            "country_name": "China",
            "download_mbps": 84.625,
            "upload_mbps": 30.317
        }, {
            "id": 162,
            "country_name": "Christmas Island",
            "download_mbps": 7.988,
            "upload_mbps": 2.731
        }, {
            "id": 166,
            "country_name": "Cocos (Keeling) Islands",
            "download_mbps": 18.238,
            "upload_mbps": 4.138
        }, {
            "id": 170,
            "country_name": "Colombia",
            "download_mbps": 11.916,
            "upload_mbps": 6.228
        }, {
            "id": 174,
            "country_name": "Comoros",
            "download_mbps": 10.385,
            "upload_mbps": 18.657
        }, {
            "id": 178,
            "country_name": "Congo",
            "download_mbps": 17.684,
            "upload_mbps": 11.955
        }, {
            "id": 184,
            "country_name": "Cook Islands",
            "download_mbps": 7.22,
            "upload_mbps": 1.865
        }, {
            "id": 188,
            "country_name": "Costa Rica",
            "download_mbps": 18.468,
            "upload_mbps": 5.835
        }, {
            "id": 191,
            "country_name": "Croatia",
            "download_mbps": 20.275,
            "upload_mbps": 8.286
        }, {
            "id": 192,
            "country_name": "Cuba",
            "download_mbps": 3.021,
            "upload_mbps": 2.938
        }, {
            "id": 196,
            "country_name": "Cyprus",
            "download_mbps": 16.409,
            "upload_mbps": 4.924
        }, {
            "id": 208,
            "country_name": "Denmark",
            "download_mbps": 90.643,
            "upload_mbps": 76.475
        }, {
            "id": 262,
            "country_name": "Djibouti",
            "download_mbps": 6.989,
            "upload_mbps": 4.661
        }, {
            "id": 212,
            "country_name": "Dominica",
            "download_mbps": 26.437,
            "upload_mbps": 19.052
        }, {
            "id": 214,
            "country_name": "Dominican Republic",
            "download_mbps": 9.742,
            "upload_mbps": 3.591
        }, {
            "id": 218,
            "country_name": "Ecuador",
            "download_mbps": 12.381,
            "upload_mbps": 11.387
        }, {
            "id": 818,
            "country_name": "Egypt",
            "download_mbps": 11.388,
            "upload_mbps": 2.486
        }, {
            "id": 222,
            "country_name": "El Salvador",
            "download_mbps": 8.322,
            "upload_mbps": 2.072
        }, {
            "id": 226,
            "country_name": "Equatorial Guinea",
            "download_mbps": 4.276,
            "upload_mbps": 3.044
        }, {
            "id": 233,
            "country_name": "Estonia",
            "download_mbps": 37.251,
            "upload_mbps": 27.286
        }, {
            "id": 231,
            "country_name": "Ethiopia",
            "download_mbps": 4.008,
            "upload_mbps": 5.164
        }, {
            "id": 234,
            "country_name": "Faroe Islands",
            "download_mbps": 34.497,
            "upload_mbps": 13.156
        }, {
            "id": 242,
            "country_name": "Fiji",
            "download_mbps": 10.594,
            "upload_mbps": 5.461
        }, {
            "id": 246,
            "country_name": "Finland",
            "download_mbps": 55.344,
            "upload_mbps": 28.366
        }, {
            "id": 250,
            "country_name": "France",
            "download_mbps": 56.388,
            "upload_mbps": 45.172
        }, {
            "id": 254,
            "country_name": "French Guiana",
            "download_mbps": 38.374,
            "upload_mbps": 22.765
        }, {
            "id": 258,
            "country_name": "French Polynesia",
            "download_mbps": 9.921,
            "upload_mbps": 2.558
        }, {
            "id": 266,
            "country_name": "Gabon",
            "download_mbps": 17.726,
            "upload_mbps": 4.752
        }, {
            "id": 270,
            "country_name": "Gambia",
            "download_mbps": 5.47,
            "upload_mbps": 4.305
        }, {
            "id": 268,
            "country_name": "Georgia",
            "download_mbps": 17.574,
            "upload_mbps": 17.926
        }, {
            "id": 276,
            "country_name": "Germany",
            "download_mbps": 56.744,
            "upload_mbps": 17.845
        }, {
            "id": 288,
            "country_name": "Ghana",
            "download_mbps": 26.152,
            "upload_mbps": 24.002
        }, {
            "id": 292,
            "country_name": "Gibraltar",
            "download_mbps": 65.328,
            "upload_mbps": 37.739
        }, {
            "id": 300,
            "country_name": "Greece",
            "download_mbps": 16.017,
            "upload_mbps": 3.286
        }, {
            "id": 304,
            "country_name": "Greenland",
            "download_mbps": 17.599,
            "upload_mbps": 7.738
        }, {
            "id": 308,
            "country_name": "Grenada",
            "download_mbps": 40.824,
            "upload_mbps": 8.42
        }, {
            "id": 312,
            "country_name": "Guadeloupe",
            "download_mbps": 24.776,
            "upload_mbps": 14.411
        }, {
            "id": 316,
            "country_name": "Guam",
            "download_mbps": 31.484,
            "upload_mbps": 6.14
        }, {
            "id": 320,
            "country_name": "Guatemala",
            "download_mbps": 8.919,
            "upload_mbps": 3.757
        }, {
            "id": 831,
            "country_name": "Guernsey",
            "download_mbps": 22.019,
            "upload_mbps": 4.894
        }, {
            "id": 324,
            "country_name": "Guinea",
            "download_mbps": 8.983,
            "upload_mbps": 6.301
        }, {
            "id": 624,
            "country_name": "Guinea-Bissau",
            "download_mbps": 10.895,
            "upload_mbps": 6.657
        }, {
            "id": 328,
            "country_name": "Guyana",
            "download_mbps": 12.187,
            "upload_mbps": 5.412
        }, {
            "id": 332,
            "country_name": "Haiti",
            "download_mbps": 8.285,
            "upload_mbps": 6.435
        }, {
            "id": 340,
            "country_name": "Honduras",
            "download_mbps": 9.292,
            "upload_mbps": 5.543
        }, {
            "id": 344,
            "country_name": "Hong Kong",
            "download_mbps": 109.389,
            "upload_mbps": 103.318
        }, {
            "id": 348,
            "country_name": "Hungary",
            "download_mbps": 67.962,
            "upload_mbps": 32.655
        }, {
            "id": 352,
            "country_name": "Iceland",
            "download_mbps": 108.134,
            "upload_mbps": 106.046
        }, {
            "id": 356,
            "country_name": "India",
            "download_mbps": 21.107,
            "upload_mbps": 19.745
        }, {
            "id": 360,
            "country_name": "Indonesia",
            "download_mbps": 11.21,
            "upload_mbps": 5.581
        }, {
            "id": 368,
            "country_name": "Iraq",
            "download_mbps": 11.607,
            "upload_mbps": 11.521
        }, {
            "id": 372,
            "country_name": "Ireland",
            "download_mbps": 45.854,
            "upload_mbps": 16.332
        }, {
            "id": 833,
            "country_name": "Isle of Man",
            "download_mbps": 28.342,
            "upload_mbps": 7.128
        }, {
            "id": 376,
            "country_name": "Israel",
            "download_mbps": 52.864,
            "upload_mbps": 11.086
        }, {
            "id": 380,
            "country_name": "Italy",
            "download_mbps": 27.102,
            "upload_mbps": 9.191
        }, {
            "id": 388,
            "country_name": "Jamaica",
            "download_mbps": 21.094,
            "upload_mbps": 6.77
        }, {
            "id": 392,
            "country_name": "Japan",
            "download_mbps": 63.838,
            "upload_mbps": 85.102
        }, {
            "id": 832,
            "country_name": "Jersey",
            "download_mbps": 119.758,
            "upload_mbps": 51.761
        }, {
            "id": 400,
            "country_name": "Jordan",
            "download_mbps": 24.133,
            "upload_mbps": 16.906
        }, {
            "id": 398,
            "country_name": "Kazakhstan",
            "download_mbps": 14.71,
            "upload_mbps": 12.738
        }, {
            "id": 404,
            "country_name": "Kenya",
            "download_mbps": 11.643,
            "upload_mbps": 11.295
        }, {
            "id": 296,
            "country_name": "Kiribati",
            "download_mbps": 4.305,
            "upload_mbps": 0.482
        }, {
            "id": 408,
            "country_name": "Korea, Democratic People's Republic of",
            "download_mbps": 52.224,
            "upload_mbps": 19.28
        }, {
            "id": 414,
            "country_name": "Kuwait",
            "download_mbps": 67.739,
            "upload_mbps": 17.547
        }, {
            "id": 417,
            "country_name": "Kyrgyzstan",
            "download_mbps": 18.766,
            "upload_mbps": 20.622
        }, {
            "id": 418,
            "country_name": "Lao People's Democratic Republic",
            "download_mbps": 19.086,
            "upload_mbps": 18.158
        }, {
            "id": 428,
            "country_name": "Latvia",
            "download_mbps": 37.417,
            "upload_mbps": 33.294
        }, {
            "id": 422,
            "country_name": "Lebanon",
            "download_mbps": 5.099,
            "upload_mbps": 4.18
        }, {
            "id": 426,
            "country_name": "Lesotho",
            "download_mbps": 12.927,
            "upload_mbps": 10.86
        }, {
            "id": 430,
            "country_name": "Liberia",
            "download_mbps": 9.76,
            "upload_mbps": 6.462
        }, {
            "id": 438,
            "country_name": "Liechtenstein",
            "download_mbps": 70.149,
            "upload_mbps": 42.728
        }, {
            "id": 440,
            "country_name": "Lithuania",
            "download_mbps": 51.419,
            "upload_mbps": 47.455
        }, {
            "id": 442,
            "country_name": "Luxembourg",
            "download_mbps": 80.456,
            "upload_mbps": 53.439
        }, {
            "id": 450,
            "country_name": "Madagascar",
            "download_mbps": 25.608,
            "upload_mbps": 27.918
        }, {
            "id": 454,
            "country_name": "Malawi",
            "download_mbps": 5.013,
            "upload_mbps": 3.957
        }, {
            "id": 458,
            "country_name": "Malaysia",
            "download_mbps": 44.208,
            "upload_mbps": 25.898
        }, {
            "id": 462,
            "country_name": "Maldives",
            "download_mbps": 9.821,
            "upload_mbps": 6.833
        }, {
            "id": 466,
            "country_name": "Mali",
            "download_mbps": 10.045,
            "upload_mbps": 5.257
        }, {
            "id": 470,
            "country_name": "Malta",
            "download_mbps": 71.434,
            "upload_mbps": 13.165
        }, {
            "id": 584,
            "country_name": "Marshall Islands",
            "download_mbps": 11.319,
            "upload_mbps": 4.778
        }, {
            "id": 474,
            "country_name": "Martinique",
            "download_mbps": 20.958,
            "upload_mbps": 10.176
        }, {
            "id": 478,
            "country_name": "Mauritania",
            "download_mbps": 3.782,
            "upload_mbps": 2.242
        }, {
            "id": 480,
            "country_name": "Mauritius",
            "download_mbps": 17.47,
            "upload_mbps": 8.629
        }, {
            "id": 175,
            "country_name": "Mayotte",
            "download_mbps": 6.324,
            "upload_mbps": 2.567
        }, {
            "id": 484,
            "country_name": "Mexico",
            "download_mbps": 17.277,
            "upload_mbps": 5.994
        }, {
            "id": 583,
            "country_name": "Micronesia, Federated States of",
            "download_mbps": 3.655,
            "upload_mbps": 2.644
        }, {
            "id": 492,
            "country_name": "Monaco",
            "download_mbps": 37.896,
            "upload_mbps": 21.803
        }, {
            "id": 496,
            "country_name": "Mongolia",
            "download_mbps": 17.559,
            "upload_mbps": 16.361
        }, {
            "id": 499,
            "country_name": "Montenegro",
            "download_mbps": 43.412,
            "upload_mbps": 5.204
        }, {
            "id": 500,
            "country_name": "Montserrat",
            "download_mbps": 9.745,
            "upload_mbps": 1.992
        }, {
            "id": 504,
            "country_name": "Morocco",
            "download_mbps": 13.802,
            "upload_mbps": 2.688
        }, {
            "id": 508,
            "country_name": "Mozambique",
            "download_mbps": 6.079,
            "upload_mbps": 6.148
        }, {
            "id": 516,
            "country_name": "Namibia",
            "download_mbps": 7.164,
            "upload_mbps": 4.867
        }, {
            "id": 520,
            "country_name": "Nauru",
            "download_mbps": 2.75,
            "upload_mbps": 2.199
        }, {
            "id": 524,
            "country_name": "Nepal",
            "download_mbps": 16.428,
            "upload_mbps": 16.0
        }, {
            "id": 540,
            "country_name": "New Caledonia",
            "download_mbps": 17.199,
            "upload_mbps": 6.623
        }, {
            "id": 554,
            "country_name": "New Zealand",
            "download_mbps": 48.852,
            "upload_mbps": 30.382
        }, {
            "id": 558,
            "country_name": "Nicaragua",
            "download_mbps": 10.369,
            "upload_mbps": 5.153
        }, {
            "id": 562,
            "country_name": "Niger",
            "download_mbps": 9.601,
            "upload_mbps": 5.268
        }, {
            "id": 566,
            "country_name": "Nigeria",
            "download_mbps": 7.105,
            "upload_mbps": 5.782
        }, {
            "id": 570,
            "country_name": "Niue",
            "download_mbps": 5.346,
            "upload_mbps": 2.371
        }, {
            "id": 574,
            "country_name": "Norfolk Island",
            "download_mbps": 11.109,
            "upload_mbps": 1.555
        }, {
            "id": 580,
            "country_name": "Northern Mariana Islands",
            "download_mbps": 31.192,
            "upload_mbps": 8.92
        }, {
            "id": 578,
            "country_name": "Norway",
            "download_mbps": 87.139,
            "upload_mbps": 79.719
        }, {
            "id": 512,
            "country_name": "Oman",
            "download_mbps": 16.461,
            "upload_mbps": 5.424
        }, {
            "id": 586,
            "country_name": "Pakistan",
            "download_mbps": 5.503,
            "upload_mbps": 3.264
        }, {
            "id": 585,
            "country_name": "Palau",
            "download_mbps": 12.714,
            "upload_mbps": 5.856
        }, {
            "id": 591,
            "country_name": "Panama",
            "download_mbps": 57.039,
            "upload_mbps": 12.699
        }, {
            "id": 598,
            "country_name": "Papua New Guinea",
            "download_mbps": 6.225,
            "upload_mbps": 4.757
        }, {
            "id": 600,
            "country_name": "Paraguay",
            "download_mbps": 16.842,
            "upload_mbps": 7.001
        }, {
            "id": 604,
            "country_name": "Peru",
            "download_mbps": 17.524,
            "upload_mbps": 4.931
        }, {
            "id": 608,
            "country_name": "Philippines",
            "download_mbps": 12.814,
            "upload_mbps": 12.32
        }, {
            "id": 616,
            "country_name": "Poland",
            "download_mbps": 48.801,
            "upload_mbps": 22.052
        }, {
            "id": 620,
            "country_name": "Portugal",
            "download_mbps": 64.621,
            "upload_mbps": 36.85
        }, {
            "id": 630,
            "country_name": "Puerto Rico",
            "download_mbps": 41.664,
            "upload_mbps": 8.23
        }, {
            "id": 634,
            "country_name": "Qatar",
            "download_mbps": 71.094,
            "upload_mbps": 46.413
        }, {
            "id": 642,
            "country_name": "Romania",
            "download_mbps": 67.386,
            "upload_mbps": 57.589
        }, {
            "id": 646,
            "country_name": "Rwanda",
            "download_mbps": 6.997,
            "upload_mbps": 6.404
        }, {
            "id": 659,
            "country_name": "Saint Kitts and Nevis",
            "download_mbps": 16.675,
            "upload_mbps": 5.986
        }, {
            "id": 662,
            "country_name": "Saint Lucia",
            "download_mbps": 31.598,
            "upload_mbps": 9.306
        }, {
            "id": 666,
            "country_name": "Saint Pierre and Miquelon",
            "download_mbps": 63.843,
            "upload_mbps": 10.689
        }, {
            "id": 670,
            "country_name": "Saint Vincent and the Grenadines",
            "download_mbps": 34.225,
            "upload_mbps": 5.525
        }, {
            "id": 882,
            "country_name": "Samoa",
            "download_mbps": 9.49,
            "upload_mbps": 11.509
        }, {
            "id": 674,
            "country_name": "San Marino",
            "download_mbps": 52.155,
            "upload_mbps": 13.478
        }, {
            "id": 678,
            "country_name": "Sao Tome and Principe",
            "download_mbps": 15.227,
            "upload_mbps": 8.801
        }, {
            "id": 682,
            "country_name": "Saudi Arabia",
            "download_mbps": 36.712,
            "upload_mbps": 14.812
        }, {
            "id": 686,
            "country_name": "Senegal",
            "download_mbps": 10.038,
            "upload_mbps": 4.316
        }, {
            "id": 688,
            "country_name": "Serbia",
            "download_mbps": 25.993,
            "upload_mbps": 7.979
        }, {
            "id": 690,
            "country_name": "Seychelles",
            "download_mbps": 15.344,
            "upload_mbps": 13.191
        }, {
            "id": 694,
            "country_name": "Sierra Leone",
            "download_mbps": 7.273,
            "upload_mbps": 3.753
        }, {
            "id": 702,
            "country_name": "Singapore",
            "download_mbps": 149.223,
            "upload_mbps": 152.307
        }, {
            "id": 703,
            "country_name": "Slovakia",
            "download_mbps": 29.917,
            "upload_mbps": 12.43
        }, {
            "id": 705,
            "country_name": "Slovenia",
            "download_mbps": 38.818,
            "upload_mbps": 13.76
        }, {
            "id": 90,
            "country_name": "Solomon Islands",
            "download_mbps": 6.423,
            "upload_mbps": 2.401
        }, {
            "id": 706,
            "country_name": "Somalia",
            "download_mbps": 6.266,
            "upload_mbps": 6.864
        }, {
            "id": 710,
            "country_name": "South Africa",
            "download_mbps": 12.747,
            "upload_mbps": 8.804
        }, {
            "id": 724,
            "country_name": "Spain",
            "download_mbps": 73.482,
            "upload_mbps": 67.135
        }, {
            "id": 144,
            "country_name": "Sri Lanka",
            "download_mbps": 20.754,
            "upload_mbps": 8.9
        }, {
            "id": 729,
            "country_name": "Sudan",
            "download_mbps": 5.639,
            "upload_mbps": 2.891
        }, {
            "id": 740,
            "country_name": "Suriname",
            "download_mbps": 7.582,
            "upload_mbps": 1.889
        }, {
            "id": 752,
            "country_name": "Sweden",
            "download_mbps": 89.24,
            "upload_mbps": 75.764
        }, {
            "id": 756,
            "country_name": "Switzerland",
            "download_mbps": 91.888,
            "upload_mbps": 46.574
        }, {
            "id": 760,
            "country_name": "Syrian Arab Republic",
            "download_mbps": 5.761,
            "upload_mbps": 6.839
        }, {
            "id": 762,
            "country_name": "Tajikistan",
            "download_mbps": 15.449,
            "upload_mbps": 14.417
        }, {
            "id": 764,
            "country_name": "Thailand",
            "download_mbps": 101.288,
            "upload_mbps": 93.652
        }, {
            "id": 626,
            "country_name": "Timor-Leste",
            "download_mbps": 5.777,
            "upload_mbps": 8.702
        }, {
            "id": 768,
            "country_name": "Togo",
            "download_mbps": 14.537,
            "upload_mbps": 3.68
        }, {
            "id": 776,
            "country_name": "Tonga",
            "download_mbps": 9.483,
            "upload_mbps": 6.553
        }, {
            "id": 780,
            "country_name": "Trinidad and Tobago",
            "download_mbps": 47.518,
            "upload_mbps": 27.56
        }, {
            "id": 788,
            "country_name": "Tunisia",
            "download_mbps": 6.945,
            "upload_mbps": 2.174
        }, {
            "id": 795,
            "country_name": "Turkmenistan",
            "download_mbps": 1.269,
            "upload_mbps": 0.915
        }, {
            "id": 796,
            "country_name": "Turks and Caicos Islands",
            "download_mbps": 13.325,
            "upload_mbps": 7.302
        }, {
            "id": 800,
            "country_name": "Uganda",
            "download_mbps": 7.831,
            "upload_mbps": 6.968
        }, {
            "id": 804,
            "country_name": "Ukraine",
            "download_mbps": 28.122,
            "upload_mbps": 30.861
        }, {
            "id": 784,
            "country_name": "United Arab Emirates",
            "download_mbps": 89.505,
            "upload_mbps": 46.708
        }, {
            "id": 834,
            "country_name": "Tanzania, United Republic of",
            "download_mbps": 9.027,
            "upload_mbps": 8.461
        }, {
            "id": 840,
            "country_name": "United States of America",
            "download_mbps": 102.337,
            "upload_mbps": 28.832
        }, {
            "id": 858,
            "country_name": "Uruguay",
            "download_mbps": 23.619,
            "upload_mbps": 8.884
        }, {
            "id": 860,
            "country_name": "Uzbekistan",
            "download_mbps": 14.358,
            "upload_mbps": 13.409
        }, {
            "id": 548,
            "country_name": "Vanuatu",
            "download_mbps": 5.637,
            "upload_mbps": 2.314
        }, {
            "id": 704,
            "country_name": "Viet Nam",
            "download_mbps": 31.889,
            "upload_mbps": 32.969
        }, {
            "id": 732,
            "country_name": "Western Sahara",
            "download_mbps": 16.162,
            "upload_mbps": 3.344
        }, {
            "id": 887,
            "country_name": "Yemen",
            "download_mbps": 2.67,
            "upload_mbps": 1.221
        }, {
            "id": 894,
            "country_name": "Zambia",
            "download_mbps": 10.045,
            "upload_mbps": 7.941
        }, {
            "id": 716,
            "country_name": "Zimbabwe",
            "download_mbps": 9.781,
            "upload_mbps": 9.694
        }]
    }
}